fio_api/__init__.py
fio_api/client.py
fio_api/exceptions.py
fio_api/models.py
fio_api/py.typed
fio_api/utils.py
fio_api-0.1.0.dist-info/WHEEL
fio_api-0.1.0.dist-info/METADATA
fio_api-0.1.0.dist-info/RECORD
