Metadata-Version: 2.3
Name: fio-api
Version: 0.1.0
Summary: Python Fio API implementaion
Author: Libor Wagner
Author-email: Libor Wagner <liborwagner@gmail.com>
License: MIT
Requires-Dist: httpx>=0.27.0,<0.28.0
Requires-Python: >=3.13
